<?xml version="1.0" encoding="UTF-8"?>

<!DOCTYPE tiles-definitions PUBLIC "-//Apache
Software Foundation//DTD Tiles Configuration 3.0//EN"
"http://tiles.apache.org/dtds/tiles-config_3_0.dtd">
<tiles-definitions>
    <definition name="baseLayout"
                template="/WEB-INF/layout/base.jsp">
        <put-attribute name="title" value="" />
        <put-attribute name="header"
                       value="/WEB-INF/layout/header.jsp" />
        <put-attribute name="content" value="" />
        <put-attribute name="footer"
                       value="/WEB-INF/layout/footer.jsp" />
    </definition>
    <definition name="home" extends="baseLayout">
        <put-attribute name="title" value="Trang chu" />
        <put-attribute name="content"
                       value="/WEB-INF/jsp/home.jsp" />
    </definition>
     <definition name="login" extends="baseLayout">
        <put-attribute name="title" value="Dang Nhap" />
        <put-attribute name="content"
                       value="/WEB-INF/jsp/login.jsp" />
    </definition>
     <definition name="register" extends="baseLayout">
        <put-attribute name="title" value="Dang Ky" />
        <put-attribute name="content"
                       value="/WEB-INF/jsp/register.jsp" />
    </definition>
     <definition name="add-inexpense" extends="baseLayout">
        <put-attribute name="title" value="Them chi phi ca nhan" />
        <put-attribute name="content"
                       value="/WEB-INF/jsp/add-inexpense.jsp" />
    </definition>
     <definition name="create-group" extends="baseLayout">
        <put-attribute name="title" value="Them chi phi" />
        <put-attribute name="content"
                       value="/WEB-INF/jsp/create-group.jsp" />
    </definition>
     <definition name="inexpense-stats" extends="baseLayout">
        <put-attribute name="title" value="Thong ke chi phi" />
        <put-attribute name="content"
                       value="/WEB-INF/jsp/inexpense-stats.jsp" />
    </definition>
</tiles-definitions>
